CubePassEncryptDPP/Cube.py
CubePassEncryptDPP/__init__.py
CubePassEncryptDPP-0.4.dist-info/LICENSE
CubePassEncryptDPP-0.4.dist-info/METADATA
CubePassEncryptDPP-0.4.dist-info/WHEEL
CubePassEncryptDPP-0.4.dist-info/top_level.txt
CubePassEncryptDPP-0.4.dist-info/RECORD
