Metadata-Version: 2.1
Name: CubePassEncryptDPP
Version: 0.4
Summary: cubePassEncryptDPP
Home-page: https://github.com/PawelTomkow/CubePassEncryptDPP
Author: Pawel Tomkow
Author-email: 236035@student.pwr.edu.pl
License: UNKNOWN
Platform: UNKNOWN
Classifier: Programming Language :: Python :: 3
Classifier: License :: OSI Approved :: MIT License
Classifier: Operating System :: OS Independent
